nonsense/__init__.py
nonsense/nonsense.py
nonsense_cli-1.4.1.dist-info/licenses/LICENSE
nonsense_cli-1.4.1.dist-info/METADATA
nonsense_cli-1.4.1.dist-info/WHEEL
nonsense_cli-1.4.1.dist-info/entry_points.txt
nonsense_cli-1.4.1.dist-info/top_level.txt
nonsense_cli-1.4.1.dist-info/RECORD
