Metadata-Version: 2.4
Name: nonsense-cli
Version: 1.4.1
Summary: A quirky command-line calculator
Author-email: Otto Latvala <halkodigital@gmail.com>
Requires-Python: >=3.9
License-File: LICENSE
Requires-Dist: colorama
Dynamic: license-file
